qurator/__init__.py
qurator/sbb/__init__.py
qurator/sbb/entropy.py
qurator/sbb/language.py
qurator/sbb/ned.py
qurator/sbb/ner.py
qurator/sbb/select.py
qurator/sbb/xml.py
qurator/topic_modeling/__init__.py
qurator/topic_modeling/cli.py
qurator/utils/__init__.py
qurator/utils/csv.py
qurator/utils/entities.py
qurator/utils/ned.py
qurator/utils/ner.py
qurator/utils/parallel.py
qurator/utils/parquet.py
qurator/utils/pickle.py
qurator/utils/qurator_data.py
qurator/utils/tsv.py
qurator/webapp/__init__.py
qurator/webapp/app.py
qurator/webapp/wsgi.py
qurator/wikidata/__init__.py
qurator/wikidata/cli.py
qurator/wikidata/entities.py
qurator/wikipedia/__init__.py
qurator/wikipedia/entities.py
qurator/wikipedia/ned.py
qurator/wikipedia/ner.py
qurator/wikipedia/xml.py
qurator_sbb_tools-0.0.2.dist-info/METADATA
qurator_sbb_tools-0.0.2.dist-info/WHEEL
qurator_sbb_tools-0.0.2.dist-info/entry_points.txt
qurator_sbb_tools-0.0.2.dist-info/top_level.txt
qurator_sbb_tools-0.0.2.dist-info/RECORD
