Metadata-Version: 2.1
Name: qurator-sbb-tools
Version: 0.0.2
Summary: Qurator
Home-page: https://github.com/qurator-spk/sbb_tools
Author: Kai Labusch, The Qurator Team
Author-email: Kai.Labusch@sbb.spk-berlin.de
License: Apache
Keywords: Qurator
Platform: UNKNOWN
Classifier: Intended Audience :: Science/Research
Classifier: License :: OSI Approved :: Apache Software License
Classifier: Programming Language :: Python :: 3
Classifier: Topic :: Scientific/Engineering :: Artificial Intelligence
Requires-Python: >=3.6.0
Requires-Dist: numpy
Requires-Dist: pandas
Requires-Dist: dask
Requires-Dist: tqdm
Requires-Dist: ipython
Requires-Dist: ipdb
Requires-Dist: jupyter
Requires-Dist: jupyter-contrib-nbextensions
Requires-Dist: matplotlib
Requires-Dist: seaborn
Requires-Dist: sklearn
Requires-Dist: click
Requires-Dist: langid
Requires-Dist: seqeval
Requires-Dist: conlleval
Requires-Dist: toolz
Requires-Dist: cloudpickle
Requires-Dist: pytest
Requires-Dist: pytest-cov
Requires-Dist: flask
Requires-Dist: flask-htpasswd
Requires-Dist: flask-cachecontrol
Requires-Dist: somajo
Requires-Dist: scipy
Requires-Dist: gensim
Requires-Dist: gunicorn
Requires-Dist: pyldavis
Requires-Dist: requests
